usepolvo/__init__.py
usepolvo/cli.py
usepolvo/config.py
usepolvo/stripe.py
usepolvo_cli-0.1.9.dist-info/METADATA
usepolvo_cli-0.1.9.dist-info/WHEEL
usepolvo_cli-0.1.9.dist-info/entry_points.txt
usepolvo_cli-0.1.9.dist-info/top_level.txt
usepolvo_cli-0.1.9.dist-info/RECORD
